{
    "area": {
        "id": 2081,
        "name": "France",
        "code": "FRA",
        "flag": "https://crests.football-data.org/773.svg"
    },
    "id": 522,
    "name": "OGC Nice",
    "shortName": "Nice",
    "tla": "NIC",
    "crest": "https://crests.football-data.org/522.png",
    "address": "35, avenue du Ray Nice 06100",
    "website": "http://www.ogcnice.com",
    "founded": 1904,
    "clubColors": "Red / Black",
    "venue": "Stade de Nice",
    "runningCompetitions": [
        {
            "id": 2174,
            "name": "Champions League Qualification",
            "code": "CLQ",
            "type": "CUP",
            "emblem": null
        },
        {
            "id": 2015,
            "name": "Ligue 1",
            "code": "FL1",
            "type": "LEAGUE",
            "emblem": "https://crests.football-data.org/FL1.png"
        }
    ],
    "coach": {
        "id": 142508,
        "firstName": "Franck",
        "lastName": "Haise",
        "name": "Franck Haise",
        "dateOfBirth": "1971-04-15",
        "nationality": "France",
        "contract": {
            "start": "2024-07",
            "until": "2027-06"
        }
    },
    "squad": [
        {
            "id": 8608,
            "name": "Yehvann Diouf",
            "position": "Goalkeeper",
            "dateOfBirth": "1999-11-16",
            "nationality": "France"
        },
        {
            "id": 8686,
            "name": "Maxime Dupé",
            "position": "Goalkeeper",
            "dateOfBirth": "1993-03-04",
            "nationality": "France"
        },
        {
            "id": 273765,
            "name": "Bartosz Żelazowski",
            "position": "Goalkeeper",
            "dateOfBirth": "2005-04-25",
            "nationality": "Poland"
        },
        {
            "id": 283103,
            "name": "Théo Bruyère",
            "position": "Goalkeeper",
            "dateOfBirth": "2006-08-17",
            "nationality": "France"
        },
        {
            "id": 202896,
            "name": "Kojo Peprah Oppong",
            "position": "Defence",
            "dateOfBirth": "2004-06-04",
            "nationality": "Ghana"
        },
        {
            "id": 282317,
            "name": "Hamza Koutoune",
            "position": "Defence",
            "dateOfBirth": "2006-09-17",
            "nationality": "Morocco"
        },
        {
            "id": 98601,
            "name": "Isak Jansson",
            "position": "Midfield",
            "dateOfBirth": "2002-01-31",
            "nationality": "Sweden"
        },
        {
            "id": 246041,
            "name": "Abdulay Bah",
            "position": "Midfield",
            "dateOfBirth": "2004-04-11",
            "nationality": "Sierra Leone"
        },
        {
            "id": 273127,
            "name": "Laurenzo Monteiro",
            "position": "Midfield",
            "dateOfBirth": "2004-05-28",
            "nationality": "France"
        },
        {
            "id": 273766,
            "name": "Djibril Coulibaly",
            "position": "Midfield",
            "dateOfBirth": "2008-11-18",
            "nationality": "France"
        },
        {
            "id": 213270,
            "name": "Mohamed Cho",
            "position": "Offence",
            "dateOfBirth": "2004-01-19",
            "nationality": "France"
        },
        {
            "id": 273432,
            "name": "Bernard Jordan Nguene",
            "position": "Offence",
            "dateOfBirth": "2006-08-04",
            "nationality": "Cameroon"
        },
        {
            "id": 279671,
            "name": "Gabin Bernardeau",
            "position": "Offence",
            "dateOfBirth": "2006-01-24",
            "nationality": "France"
        },
        {
            "id": 168667,
            "name": "Antoine Mendy",
            "position": "Right-Back",
            "dateOfBirth": "2004-05-27",
            "nationality": "France"
        },
        {
            "id": 136721,
            "name": "Melvin Bard",
            "position": "Left-Back",
            "dateOfBirth": "2000-11-06",
            "nationality": "France"
        },
        {
            "id": 123508,
            "name": "Hicham Boudaoui",
            "position": "Central Midfield",
            "dateOfBirth": "1999-09-23",
            "nationality": "Algeria"
        },
        {
            "id": 123206,
            "name": "Salis Abdul Samed",
            "position": "Defensive Midfield",
            "dateOfBirth": "2000-03-26",
            "nationality": "Ghana"
        },
        {
            "id": 113427,
            "name": "Terem Moffi",
            "position": "Centre-Forward",
            "dateOfBirth": "1999-05-25",
            "nationality": "Nigeria"
        },
        {
            "id": 99394,
            "name": "Ali El Abdi",
            "position": "Left-Back",
            "dateOfBirth": "1993-12-20",
            "nationality": "Tunisia"
        },
        {
            "id": 76723,
            "name": "Sofiane Diop",
            "position": "Left Winger",
            "dateOfBirth": "2000-06-09",
            "nationality": "France"
        },
        {
            "id": 8469,
            "name": "Tanguy Ndombèlé",
            "position": "Central Midfield",
            "dateOfBirth": "1996-12-28",
            "nationality": "France"
        },
        {
            "id": 8425,
            "name": "Dante",
            "position": "Centre-Back",
            "dateOfBirth": "1983-10-18",
            "nationality": "Brazil"
        },
        {
            "id": 8355,
            "name": "Morgan Sanson",
            "position": "Central Midfield",
            "dateOfBirth": "1994-08-18",
            "nationality": "France"
        },
        {
            "id": 7448,
            "name": "Pablo Rosario",
            "position": "Defensive Midfield",
            "dateOfBirth": "1997-01-07",
            "nationality": "Dominican Republic"
        },
        {
            "id": 4121,
            "name": "Jérémie Boga",
            "position": "Left Winger",
            "dateOfBirth": "1997-01-03",
            "nationality": "Ivory Coast"
        },
        {
            "id": 1023,
            "name": "Jonathan Clauss",
            "position": "Right-Back",
            "dateOfBirth": "1992-09-25",
            "nationality": "France"
        },
        {
            "id": 245563,
            "name": "Mohamed Abdelmonem",
            "position": "Centre-Back",
            "dateOfBirth": "1999-02-01",
            "nationality": "Egypt"
        },
        {
            "id": 220121,
            "name": "Amidou Doumbouya",
            "position": "Centre-Back",
            "dateOfBirth": "2007-08-05",
            "nationality": "France"
        },
        {
            "id": 204237,
            "name": "Tom Louchet",
            "position": "Right Midfield",
            "dateOfBirth": "2003-05-04",
            "nationality": "France"
        },
        {
            "id": 192153,
            "name": "Moise Bombito",
            "position": "Centre-Back",
            "dateOfBirth": "2000-03-30",
            "nationality": "Canada"
        },
        {
            "id": 185007,
            "name": "Badredine Bouanani",
            "position": "Right Winger",
            "dateOfBirth": "2004-12-08",
            "nationality": "Algeria"
        },
        {
            "id": 181927,
            "name": "Bilal Brahimi",
            "position": "Left Winger",
            "dateOfBirth": "2000-03-14",
            "nationality": "Algeria"
        },
        {
            "id": 172057,
            "name": "Youssouf Ndayishimiye",
            "position": "Centre-Back",
            "dateOfBirth": "1998-10-27",
            "nationality": "Burundi"
        }
    ],
    "staff": [],
    "lastUpdated": "2022-02-19T08:51:11Z"
}