{
    "id": 158717,
    "name": "Federico Caia",
    "firstName": "Federico",
    "lastName": "Caia",
    "dateOfBirth": "2003-04-21",
    "nationality": "Italy",
    "section": "Offence",
    "position": "Offence",
    "shirtNumber": null,
    "lastUpdated": "2023-06-02T09:55:15Z",
    "currentTeam": {
        "area": {
            "id": 2114,
            "name": "Italy",
            "code": "ITA",
            "flag": "https://crests.football-data.org/784.svg"
        },
        "id": 450,
        "name": "Hellas Verona FC",
        "shortName": "Verona",
        "tla": "HVE",
        "crest": "https://crests.football-data.org/450.png",
        "address": "Via Evangelista Torricelli, 37 Verona 37136",
        "website": "http://www.hellasverona.it",
        "founded": 1903,
        "clubColors": "Yellow / Blue",
        "venue": "Stadio Marc'Antonio Bentegodi",
        "runningCompetitions": [
            {
                "id": 2019,
                "name": "Serie A",
                "code": "SA",
                "type": "LEAGUE",
                "emblem": "https://crests.football-data.org/SA.png"
            }
        ],
        "contract": {
            "start": "2025-07",
            "until": "2026-06"
        }
    }
}