{
    "id": 177842,
    "name": "Tomas Araujo",
    "firstName": "",
    "lastName": "Tomás Araújo",
    "dateOfBirth": "2002-05-16",
    "nationality": "Portugal",
    "section": "Centre-Back",
    "position": "Defence",
    "shirtNumber": 44,
    "lastUpdated": "2024-11-01T22:50:30Z",
    "currentTeam": {
        "area": {
            "id": 2187,
            "name": "Portugal",
            "code": "POR",
            "flag": "https://crests.football-data.org/765.svg"
        },
        "id": 5537,
        "name": "Sport Lisboa e Benfica B",
        "shortName": "SL Benfica B",
        "tla": "SLB",
        "crest": "https://crests.football-data.org/5537.png",
        "address": "Av. General Norton de Matos 1500, Apartado Nº 4100 Lisboa 1501-805",
        "website": "http://www.slbenfica.pt",
        "founded": 1904,
        "clubColors": "Red / White",
        "venue": "Caixa Futebol Campus",
        "runningCompetitions": [
            {
                "id": 2096,
                "name": "Liga2 Cabovisão",
                "code": "PSL",
                "type": "LEAGUE",
                "emblem": null
            }
        ],
        "contract": {
            "start": "2025-08",
            "until": "2025-08"
        }
    }
}