{
    "id": 261437,
    "name": "Florian Micheler",
    "firstName": "Florian",
    "lastName": "Micheler",
    "dateOfBirth": "2005-05-17",
    "nationality": "Austria",
    "section": "Midfield",
    "position": "Midfield",
    "shirtNumber": 20,
    "lastUpdated": "2024-10-09T09:41:17Z",
    "currentTeam": {
        "area": {
            "id": 2088,
            "name": "Germany",
            "code": "DEU",
            "flag": "https://crests.football-data.org/759.svg"
        },
        "id": 38,
        "name": "Arminia Bielefeld",
        "shortName": "Bielefeld",
        "tla": "BIE",
        "crest": "https://crests.football-data.org/38.png",
        "address": "Melanchthonstraße 31a Bielefeld 33615",
        "website": "http://www.arminia-bielefeld.de",
        "founded": 1905,
        "clubColors": "Black / White / Blue",
        "venue": "SchücoArena Kunstrasenplatz",
        "runningCompetitions": [
            {
                "id": 2011,
                "name": "DFB-Pokal",
                "code": "DFB",
                "type": "CUP",
                "emblem": "https://crests.football-data.org/DFB_CUP.png"
            },
            {
                "id": 2004,
                "name": "2. Bundesliga",
                "code": "BL2",
                "type": "LEAGUE",
                "emblem": "https://crests.football-data.org/BL2.png"
            }
        ],
        "contract": {
            "start": "2025-07",
            "until": "2026-06"
        }
    }
}