{
    "id": 278561,
    "name": "Lander Pinillos",
    "firstName": "",
    "lastName": "Lander Pinillos",
    "dateOfBirth": "2003-10-06",
    "nationality": "Spain",
    "section": "Offence",
    "position": "Offence",
    "shirtNumber": 28,
    "lastUpdated": "2025-05-25T09:42:15Z",
    "currentTeam": {
        "area": {
            "id": 2224,
            "name": "Spain",
            "code": "ESP",
            "flag": "https://crests.football-data.org/760.svg"
        },
        "id": 263,
        "name": "Deportivo Alavés",
        "shortName": "Alavés",
        "tla": "ALA",
        "crest": "https://crests.football-data.org/263.png",
        "address": "Mendizorroza, Paseo Cervantes, s/n Vitoria 01007",
        "website": "http://www.alaves.com",
        "founded": 1921,
        "clubColors": "Blue / White",
        "venue": "Estadio de Mendizorroza",
        "runningCompetitions": [
            {
                "id": 2014,
                "name": "Primera Division",
                "code": "PD",
                "type": "LEAGUE",
                "emblem": "https://crests.football-data.org/laliga.png"
            }
        ],
        "contract": {
            "start": "2025-05",
            "until": "2027-06"
        }
    }
}