{
    "id": 32449,
    "name": "Luis Milla",
    "firstName": "",
    "lastName": "Luis Milla",
    "dateOfBirth": "1994-10-07",
    "nationality": "Spain",
    "section": "Central Midfield",
    "position": "Midfield",
    "shirtNumber": 5,
    "lastUpdated": "2024-08-12T11:57:14Z",
    "currentTeam": {
        "area": {
            "id": 2224,
            "name": "Spain",
            "code": "ESP",
            "flag": "https://crests.football-data.org/760.svg"
        },
        "id": 82,
        "name": "Getafe CF",
        "shortName": "Getafe",
        "tla": "GET",
        "crest": "https://crests.football-data.org/82.png",
        "address": "Avenida Teresa de Calcuta, s/n Getafe 28903",
        "website": "http://www.getafecf.com",
        "founded": 1946,
        "clubColors": "Blue / White",
        "venue": "Coliseum Alfonso Pérez",
        "runningCompetitions": [
            {
                "id": 2014,
                "name": "Primera Division",
                "code": "PD",
                "type": "LEAGUE",
                "emblem": "https://crests.football-data.org/laliga.png"
            }
        ],
        "contract": {
            "start": "2022-07",
            "until": "2027-06"
        }
    }
}