{
    "id": 37539,
    "name": "André Almeida",
    "firstName": "",
    "lastName": "André Almeida",
    "dateOfBirth": "2000-05-30",
    "nationality": "Portugal",
    "section": "Attacking Midfield",
    "position": "Midfield",
    "shirtNumber": 10,
    "lastUpdated": "2024-11-28T13:36:11Z",
    "currentTeam": {
        "area": {
            "id": 2224,
            "name": "Spain",
            "code": "ESP",
            "flag": "https://crests.football-data.org/760.svg"
        },
        "id": 95,
        "name": "Valencia CF",
        "shortName": "Valencia",
        "tla": "VAL",
        "crest": "https://crests.football-data.org/95.png",
        "address": "Plaza del Valencia Club de Fútbol, 2 Valencia 46010",
        "website": "http://www.valenciacf.com",
        "founded": 1919,
        "clubColors": "White / Orange / Black",
        "venue": "Estadio de Mestalla",
        "runningCompetitions": [
            {
                "id": 2014,
                "name": "Primera Division",
                "code": "PD",
                "type": "LEAGUE",
                "emblem": "https://crests.football-data.org/laliga.png"
            }
        ],
        "contract": {
            "start": "2023-07",
            "until": "2028-06"
        }
    }
}