{
    "id": 97789,
    "name": "Elia Petrelli",
    "firstName": "Elia",
    "lastName": "Petrelli",
    "dateOfBirth": "2001-08-15",
    "nationality": "Italy",
    "section": "Offence",
    "position": "Offence",
    "shirtNumber": 7,
    "lastUpdated": "2023-09-19T09:50:14Z",
    "currentTeam": {
        "area": {
            "id": 2114,
            "name": "Italy",
            "code": "ITA",
            "flag": "https://crests.football-data.org/784.svg"
        },
        "id": 11288,
        "name": "Forlì FC",
        "shortName": "Forlì",
        "tla": "",
        "crest": "https://crests.football-data.org/11288.png",
        "address": "null null null",
        "website": null,
        "founded": null,
        "clubColors": null,
        "venue": null,
        "runningCompetitions": [
            {
                "id": 2163,
                "name": "Serie C - Girone B",
                "code": "ISCB",
                "type": "LEAGUE",
                "emblem": null
            }
        ],
        "contract": {
            "start": "2024-08",
            "until": "2026-06"
        }
    }
}